hyunwooTest/test.py
hyunwooTest/test1.py
hyunwooTest/test2.py
hyunwooTest-0.0.0.2.dist-info/METADATA
hyunwooTest-0.0.0.2.dist-info/WHEEL
hyunwooTest-0.0.0.2.dist-info/top_level.txt
hyunwooTest-0.0.0.2.dist-info/RECORD
