Metadata-Version: 2.1
Name: hyunwooTest
Version: 0.0.0.2
Summary: My First Test Package
Home-page: https://blog.naver.com/dn3311
Author: hyunwoo_kim
Author-email: dn3311@naver.com
License: MIT
Platform: UNKNOWN
Requires-Python: >=3
